{
  "annotations": {
    "list": [
      {
        "builtIn": 1,
        "datasource": {
          "type": "grafana",
          "uid": "-- Grafana --"
        },
        "enable": true,
        "hide": true,
        "iconColor": "rgba(0, 211, 255, 1)",
        "name": "Annotations & Alerts",
        "type": "dashboard"
      }
    ]
  },
  "editable": true,
  "fiscalYearStartMonth": 0,
  "graphTooltip": 1,
  "id": null,
  "links": [],
  "panels": [
    {
      "id": 1,
      "title": "MySQL QPS (Queries Per Second)",
      "description": "Number of queries executed per second",
      "type": "timeseries",
      "gridPos": {
        "h": 8,
        "w": 12,
        "x": 0,
        "y": 0
      },
      "datasource": {
        "type": "prometheus",
        "uid": "prom"
      },
      "fieldConfig": {
        "defaults": {
          "color": {
            "mode": "palette-classic"
          },
          "custom": {
            "axisBorderShow": false,
            "axisCenteredZero": false,
            "axisColorMode": "text",
            "axisLabel": "Queries/s",
            "axisPlacement": "auto",
            "barAlignment": 0,
            "drawStyle": "line",
            "fillOpacity": 15,
            "gradientMode": "none",
            "hideFrom": {
              "legend": false,
              "tooltip": false,
              "viz": false
            },
            "insertNulls": false,
            "lineInterpolation": "smooth",
            "lineWidth": 2,
            "pointSize": 5,
            "scaleDistribution": {
              "type": "linear"
            },
            "showPoints": "never",
            "spanNulls": false,
            "stacking": {
              "group": "A",
              "mode": "none"
            },
            "thresholdsStyle": {
              "mode": "off"
            }
          },
          "unit": "ops",
          "decimals": 2,
          "thresholds": {
            "mode": "absolute",
            "steps": [
              {
                "color": "green",
                "value": null
              }
            ]
          }
        },
        "overrides": []
      },
      "options": {
        "legend": {
          "calcs": ["mean", "max", "lastNotNull"],
          "displayMode": "table",
          "placement": "bottom",
          "showLegend": true
        },
        "tooltip": {
          "mode": "multi",
          "sort": "desc"
        }
      },
      "targets": [
        {
          "datasource": {
            "type": "prometheus",
            "uid": "prom"
          },
          "expr": "rate(mysql_global_status_queries[1m])",
          "legendFormat": "QPS",
          "refId": "A"
        }
      ]
    },
    {
      "id": 2,
      "title": "MySQL Connections",
      "description": "Current connected threads vs max allowed connections",
      "type": "timeseries",
      "gridPos": {
        "h": 8,
        "w": 12,
        "x": 12,
        "y": 0
      },
      "datasource": {
        "type": "prometheus",
        "uid": "prom"
      },
      "fieldConfig": {
        "defaults": {
          "color": {
            "mode": "palette-classic"
          },
          "custom": {
            "axisBorderShow": false,
            "axisCenteredZero": false,
            "axisColorMode": "text",
            "axisLabel": "Connections",
            "axisPlacement": "auto",
            "barAlignment": 0,
            "drawStyle": "line",
            "fillOpacity": 10,
            "gradientMode": "none",
            "hideFrom": {
              "legend": false,
              "tooltip": false,
              "viz": false
            },
            "insertNulls": false,
            "lineInterpolation": "smooth",
            "lineWidth": 2,
            "pointSize": 5,
            "scaleDistribution": {
              "type": "linear"
            },
            "showPoints": "never",
            "spanNulls": false,
            "stacking": {
              "group": "A",
              "mode": "none"
            },
            "thresholdsStyle": {
              "mode": "off"
            }
          },
          "unit": "short",
          "decimals": 0,
          "thresholds": {
            "mode": "absolute",
            "steps": [
              {
                "color": "green",
                "value": null
              }
            ]
          }
        },
        "overrides": [
          {
            "matcher": {
              "id": "byName",
              "options": "Max Connections"
            },
            "properties": [
              {
                "id": "custom.lineStyle",
                "value": {
                  "dash": [10, 10],
                  "fill": "dash"
                }
              },
              {
                "id": "color",
                "value": {
                  "fixedColor": "red",
                  "mode": "fixed"
                }
              },
              {
                "id": "custom.fillOpacity",
                "value": 0
              }
            ]
          }
        ]
      },
      "options": {
        "legend": {
          "calcs": ["mean", "max", "lastNotNull"],
          "displayMode": "table",
          "placement": "bottom",
          "showLegend": true
        },
        "tooltip": {
          "mode": "multi",
          "sort": "desc"
        }
      },
      "targets": [
        {
          "datasource": {
            "type": "prometheus",
            "uid": "prom"
          },
          "expr": "mysql_global_status_threads_connected",
          "legendFormat": "Connected Threads",
          "refId": "A"
        },
        {
          "datasource": {
            "type": "prometheus",
            "uid": "prom"
          },
          "expr": "mysql_global_variables_max_connections",
          "legendFormat": "Max Connections",
          "refId": "B"
        }
      ]
    },
    {
      "id": 3,
      "title": "MySQL Thread Activity",
      "description": "Running threads vs connected threads",
      "type": "timeseries",
      "gridPos": {
        "h": 8,
        "w": 12,
        "x": 0,
        "y": 8
      },
      "datasource": {
        "type": "prometheus",
        "uid": "prom"
      },
      "fieldConfig": {
        "defaults": {
          "color": {
            "mode": "palette-classic"
          },
          "custom": {
            "axisBorderShow": false,
            "axisCenteredZero": false,
            "axisColorMode": "text",
            "axisLabel": "Threads",
            "axisPlacement": "auto",
            "barAlignment": 0,
            "drawStyle": "line",
            "fillOpacity": 15,
            "gradientMode": "none",
            "hideFrom": {
              "legend": false,
              "tooltip": false,
              "viz": false
            },
            "insertNulls": false,
            "lineInterpolation": "smooth",
            "lineWidth": 2,
            "pointSize": 5,
            "scaleDistribution": {
              "type": "linear"
            },
            "showPoints": "never",
            "spanNulls": false,
            "stacking": {
              "group": "A",
              "mode": "none"
            },
            "thresholdsStyle": {
              "mode": "off"
            }
          },
          "unit": "short",
          "decimals": 0,
          "thresholds": {
            "mode": "absolute",
            "steps": [
              {
                "color": "green",
                "value": null
              }
            ]
          }
        },
        "overrides": []
      },
      "options": {
        "legend": {
          "calcs": ["mean", "max", "lastNotNull"],
          "displayMode": "table",
          "placement": "bottom",
          "showLegend": true
        },
        "tooltip": {
          "mode": "multi",
          "sort": "desc"
        }
      },
      "targets": [
        {
          "datasource": {
            "type": "prometheus",
            "uid": "prom"
          },
          "expr": "mysql_global_status_threads_running",
          "legendFormat": "Threads Running",
          "refId": "A"
        },
        {
          "datasource": {
            "type": "prometheus",
            "uid": "prom"
          },
          "expr": "mysql_global_status_threads_connected",
          "legendFormat": "Threads Connected",
          "refId": "B"
        }
      ]
    },
    {
      "id": 4,
      "title": "InnoDB Buffer Pool Size",
      "description": "InnoDB buffer pool data size vs total allocated size",
      "type": "timeseries",
      "gridPos": {
        "h": 8,
        "w": 12,
        "x": 12,
        "y": 8
      },
      "datasource": {
        "type": "prometheus",
        "uid": "prom"
      },
      "fieldConfig": {
        "defaults": {
          "color": {
            "mode": "palette-classic"
          },
          "custom": {
            "axisBorderShow": false,
            "axisCenteredZero": false,
            "axisColorMode": "text",
            "axisLabel": "Size",
            "axisPlacement": "auto",
            "barAlignment": 0,
            "drawStyle": "line",
            "fillOpacity": 15,
            "gradientMode": "none",
            "hideFrom": {
              "legend": false,
              "tooltip": false,
              "viz": false
            },
            "insertNulls": false,
            "lineInterpolation": "smooth",
            "lineWidth": 2,
            "pointSize": 5,
            "scaleDistribution": {
              "type": "linear"
            },
            "showPoints": "never",
            "spanNulls": false,
            "stacking": {
              "group": "A",
              "mode": "none"
            },
            "thresholdsStyle": {
              "mode": "off"
            }
          },
          "unit": "bytes",
          "decimals": 2,
          "thresholds": {
            "mode": "absolute",
            "steps": [
              {
                "color": "green",
                "value": null
              }
            ]
          }
        },
        "overrides": [
          {
            "matcher": {
              "id": "byName",
              "options": "Buffer Pool Size (Allocated)"
            },
            "properties": [
              {
                "id": "custom.lineStyle",
                "value": {
                  "dash": [10, 10],
                  "fill": "dash"
                }
              },
              {
                "id": "color",
                "value": {
                  "fixedColor": "red",
                  "mode": "fixed"
                }
              },
              {
                "id": "custom.fillOpacity",
                "value": 0
              }
            ]
          }
        ]
      },
      "options": {
        "legend": {
          "calcs": ["mean", "max", "lastNotNull"],
          "displayMode": "table",
          "placement": "bottom",
          "showLegend": true
        },
        "tooltip": {
          "mode": "multi",
          "sort": "desc"
        }
      },
      "targets": [
        {
          "datasource": {
            "type": "prometheus",
            "uid": "prom"
          },
          "expr": "mysql_global_status_innodb_buffer_pool_bytes_data",
          "legendFormat": "Buffer Pool Data",
          "refId": "A"
        },
        {
          "datasource": {
            "type": "prometheus",
            "uid": "prom"
          },
          "expr": "mysql_global_variables_innodb_buffer_pool_size",
          "legendFormat": "Buffer Pool Size (Allocated)",
          "refId": "B"
        }
      ]
    },
    {
      "id": 5,
      "title": "InnoDB Buffer Pool Hit Rate",
      "description": "Ratio of read requests served from buffer pool vs disk reads (higher is better)",
      "type": "timeseries",
      "gridPos": {
        "h": 8,
        "w": 12,
        "x": 0,
        "y": 16
      },
      "datasource": {
        "type": "prometheus",
        "uid": "prom"
      },
      "fieldConfig": {
        "defaults": {
          "color": {
            "mode": "palette-classic"
          },
          "custom": {
            "axisBorderShow": false,
            "axisCenteredZero": false,
            "axisColorMode": "text",
            "axisLabel": "Hit Rate",
            "axisPlacement": "auto",
            "barAlignment": 0,
            "drawStyle": "line",
            "fillOpacity": 15,
            "gradientMode": "none",
            "hideFrom": {
              "legend": false,
              "tooltip": false,
              "viz": false
            },
            "insertNulls": false,
            "lineInterpolation": "smooth",
            "lineWidth": 2,
            "pointSize": 5,
            "scaleDistribution": {
              "type": "linear"
            },
            "showPoints": "never",
            "spanNulls": false,
            "stacking": {
              "group": "A",
              "mode": "none"
            },
            "thresholdsStyle": {
              "mode": "line+area"
            }
          },
          "unit": "percentunit",
          "decimals": 4,
          "min": 0,
          "max": 1,
          "thresholds": {
            "mode": "absolute",
            "steps": [
              {
                "color": "red",
                "value": null
              },
              {
                "color": "yellow",
                "value": 0.95
              },
              {
                "color": "green",
                "value": 0.99
              }
            ]
          }
        },
        "overrides": []
      },
      "options": {
        "legend": {
          "calcs": ["mean", "min", "lastNotNull"],
          "displayMode": "table",
          "placement": "bottom",
          "showLegend": true
        },
        "tooltip": {
          "mode": "multi",
          "sort": "desc"
        }
      },
      "targets": [
        {
          "datasource": {
            "type": "prometheus",
            "uid": "prom"
          },
          "expr": "rate(mysql_global_status_innodb_buffer_pool_read_requests[1m]) / (rate(mysql_global_status_innodb_buffer_pool_read_requests[1m]) + rate(mysql_global_status_innodb_buffer_pool_reads[1m]))",
          "legendFormat": "Buffer Pool Hit Rate",
          "refId": "A"
        }
      ]
    },
    {
      "id": 6,
      "title": "MySQL Network Traffic",
      "description": "Rate of bytes received and sent by MySQL",
      "type": "timeseries",
      "gridPos": {
        "h": 8,
        "w": 12,
        "x": 12,
        "y": 16
      },
      "datasource": {
        "type": "prometheus",
        "uid": "prom"
      },
      "fieldConfig": {
        "defaults": {
          "color": {
            "mode": "palette-classic"
          },
          "custom": {
            "axisBorderShow": false,
            "axisCenteredZero": false,
            "axisColorMode": "text",
            "axisLabel": "Throughput",
            "axisPlacement": "auto",
            "barAlignment": 0,
            "drawStyle": "line",
            "fillOpacity": 15,
            "gradientMode": "none",
            "hideFrom": {
              "legend": false,
              "tooltip": false,
              "viz": false
            },
            "insertNulls": false,
            "lineInterpolation": "smooth",
            "lineWidth": 2,
            "pointSize": 5,
            "scaleDistribution": {
              "type": "linear"
            },
            "showPoints": "never",
            "spanNulls": false,
            "stacking": {
              "group": "A",
              "mode": "none"
            },
            "thresholdsStyle": {
              "mode": "off"
            }
          },
          "unit": "Bps",
          "decimals": 2,
          "thresholds": {
            "mode": "absolute",
            "steps": [
              {
                "color": "green",
                "value": null
              }
            ]
          }
        },
        "overrides": [
          {
            "matcher": {
              "id": "byName",
              "options": "Bytes Received"
            },
            "properties": [
              {
                "id": "color",
                "value": {
                  "fixedColor": "green",
                  "mode": "fixed"
                }
              }
            ]
          },
          {
            "matcher": {
              "id": "byName",
              "options": "Bytes Sent"
            },
            "properties": [
              {
                "id": "color",
                "value": {
                  "fixedColor": "blue",
                  "mode": "fixed"
                }
              }
            ]
          }
        ]
      },
      "options": {
        "legend": {
          "calcs": ["mean", "max", "lastNotNull"],
          "displayMode": "table",
          "placement": "bottom",
          "showLegend": true
        },
        "tooltip": {
          "mode": "multi",
          "sort": "desc"
        }
      },
      "targets": [
        {
          "datasource": {
            "type": "prometheus",
            "uid": "prom"
          },
          "expr": "rate(mysql_global_status_bytes_received[1m])",
          "legendFormat": "Bytes Received",
          "refId": "A"
        },
        {
          "datasource": {
            "type": "prometheus",
            "uid": "prom"
          },
          "expr": "rate(mysql_global_status_bytes_sent[1m])",
          "legendFormat": "Bytes Sent",
          "refId": "B"
        }
      ]
    },
    {
      "id": 7,
      "title": "MySQL Slow Queries",
      "description": "Rate of slow queries per second",
      "type": "timeseries",
      "gridPos": {
        "h": 8,
        "w": 12,
        "x": 0,
        "y": 24
      },
      "datasource": {
        "type": "prometheus",
        "uid": "prom"
      },
      "fieldConfig": {
        "defaults": {
          "color": {
            "fixedColor": "orange",
            "mode": "fixed"
          },
          "custom": {
            "axisBorderShow": false,
            "axisCenteredZero": false,
            "axisColorMode": "text",
            "axisLabel": "Slow Queries/s",
            "axisPlacement": "auto",
            "barAlignment": 0,
            "drawStyle": "line",
            "fillOpacity": 20,
            "gradientMode": "none",
            "hideFrom": {
              "legend": false,
              "tooltip": false,
              "viz": false
            },
            "insertNulls": false,
            "lineInterpolation": "smooth",
            "lineWidth": 2,
            "pointSize": 5,
            "scaleDistribution": {
              "type": "linear"
            },
            "showPoints": "never",
            "spanNulls": false,
            "stacking": {
              "group": "A",
              "mode": "none"
            },
            "thresholdsStyle": {
              "mode": "off"
            }
          },
          "unit": "ops",
          "decimals": 4,
          "thresholds": {
            "mode": "absolute",
            "steps": [
              {
                "color": "green",
                "value": null
              }
            ]
          }
        },
        "overrides": []
      },
      "options": {
        "legend": {
          "calcs": ["mean", "max", "lastNotNull"],
          "displayMode": "table",
          "placement": "bottom",
          "showLegend": true
        },
        "tooltip": {
          "mode": "multi",
          "sort": "desc"
        }
      },
      "targets": [
        {
          "datasource": {
            "type": "prometheus",
            "uid": "prom"
          },
          "expr": "rate(mysql_global_status_slow_queries[1m])",
          "legendFormat": "Slow Queries",
          "refId": "A"
        }
      ]
    },
    {
      "id": 8,
      "title": "MySQL Table Locks",
      "description": "Rate of table locks waited vs immediately granted",
      "type": "timeseries",
      "gridPos": {
        "h": 8,
        "w": 12,
        "x": 12,
        "y": 24
      },
      "datasource": {
        "type": "prometheus",
        "uid": "prom"
      },
      "fieldConfig": {
        "defaults": {
          "color": {
            "mode": "palette-classic"
          },
          "custom": {
            "axisBorderShow": false,
            "axisCenteredZero": false,
            "axisColorMode": "text",
            "axisLabel": "Locks/s",
            "axisPlacement": "auto",
            "barAlignment": 0,
            "drawStyle": "line",
            "fillOpacity": 15,
            "gradientMode": "none",
            "hideFrom": {
              "legend": false,
              "tooltip": false,
              "viz": false
            },
            "insertNulls": false,
            "lineInterpolation": "smooth",
            "lineWidth": 2,
            "pointSize": 5,
            "scaleDistribution": {
              "type": "linear"
            },
            "showPoints": "never",
            "spanNulls": false,
            "stacking": {
              "group": "A",
              "mode": "none"
            },
            "thresholdsStyle": {
              "mode": "off"
            }
          },
          "unit": "ops",
          "decimals": 4,
          "thresholds": {
            "mode": "absolute",
            "steps": [
              {
                "color": "green",
                "value": null
              }
            ]
          }
        },
        "overrides": [
          {
            "matcher": {
              "id": "byName",
              "options": "Table Locks Waited"
            },
            "properties": [
              {
                "id": "color",
                "value": {
                  "fixedColor": "red",
                  "mode": "fixed"
                }
              }
            ]
          },
          {
            "matcher": {
              "id": "byName",
              "options": "Table Locks Immediate"
            },
            "properties": [
              {
                "id": "color",
                "value": {
                  "fixedColor": "green",
                  "mode": "fixed"
                }
              }
            ]
          }
        ]
      },
      "options": {
        "legend": {
          "calcs": ["mean", "max", "lastNotNull"],
          "displayMode": "table",
          "placement": "bottom",
          "showLegend": true
        },
        "tooltip": {
          "mode": "multi",
          "sort": "desc"
        }
      },
      "targets": [
        {
          "datasource": {
            "type": "prometheus",
            "uid": "prom"
          },
          "expr": "rate(mysql_global_status_table_locks_waited[1m])",
          "legendFormat": "Table Locks Waited",
          "refId": "A"
        },
        {
          "datasource": {
            "type": "prometheus",
            "uid": "prom"
          },
          "expr": "rate(mysql_global_status_table_locks_immediate[1m])",
          "legendFormat": "Table Locks Immediate",
          "refId": "B"
        }
      ]
    },
    {
      "id": 9,
      "title": "MySQL Commands",
      "description": "Rate of SELECT, INSERT, UPDATE, DELETE commands per second",
      "type": "timeseries",
      "gridPos": {
        "h": 8,
        "w": 24,
        "x": 0,
        "y": 32
      },
      "datasource": {
        "type": "prometheus",
        "uid": "prom"
      },
      "fieldConfig": {
        "defaults": {
          "color": {
            "mode": "palette-classic"
          },
          "custom": {
            "axisBorderShow": false,
            "axisCenteredZero": false,
            "axisColorMode": "text",
            "axisLabel": "Commands/s",
            "axisPlacement": "auto",
            "barAlignment": 0,
            "drawStyle": "line",
            "fillOpacity": 15,
            "gradientMode": "none",
            "hideFrom": {
              "legend": false,
              "tooltip": false,
              "viz": false
            },
            "insertNulls": false,
            "lineInterpolation": "smooth",
            "lineWidth": 2,
            "pointSize": 5,
            "scaleDistribution": {
              "type": "linear"
            },
            "showPoints": "never",
            "spanNulls": false,
            "stacking": {
              "group": "A",
              "mode": "none"
            },
            "thresholdsStyle": {
              "mode": "off"
            }
          },
          "unit": "ops",
          "decimals": 2,
          "thresholds": {
            "mode": "absolute",
            "steps": [
              {
                "color": "green",
                "value": null
              }
            ]
          }
        },
        "overrides": [
          {
            "matcher": {
              "id": "byName",
              "options": "SELECT"
            },
            "properties": [
              {
                "id": "color",
                "value": {
                  "fixedColor": "green",
                  "mode": "fixed"
                }
              }
            ]
          },
          {
            "matcher": {
              "id": "byName",
              "options": "INSERT"
            },
            "properties": [
              {
                "id": "color",
                "value": {
                  "fixedColor": "blue",
                  "mode": "fixed"
                }
              }
            ]
          },
          {
            "matcher": {
              "id": "byName",
              "options": "UPDATE"
            },
            "properties": [
              {
                "id": "color",
                "value": {
                  "fixedColor": "yellow",
                  "mode": "fixed"
                }
              }
            ]
          },
          {
            "matcher": {
              "id": "byName",
              "options": "DELETE"
            },
            "properties": [
              {
                "id": "color",
                "value": {
                  "fixedColor": "red",
                  "mode": "fixed"
                }
              }
            ]
          }
        ]
      },
      "options": {
        "legend": {
          "calcs": ["mean", "max", "lastNotNull"],
          "displayMode": "table",
          "placement": "bottom",
          "showLegend": true
        },
        "tooltip": {
          "mode": "multi",
          "sort": "desc"
        }
      },
      "targets": [
        {
          "datasource": {
            "type": "prometheus",
            "uid": "prom"
          },
          "expr": "rate(mysql_global_status_commands_total{command=\"select\"}[1m])",
          "legendFormat": "SELECT",
          "refId": "A"
        },
        {
          "datasource": {
            "type": "prometheus",
            "uid": "prom"
          },
          "expr": "rate(mysql_global_status_commands_total{command=\"insert\"}[1m])",
          "legendFormat": "INSERT",
          "refId": "B"
        },
        {
          "datasource": {
            "type": "prometheus",
            "uid": "prom"
          },
          "expr": "rate(mysql_global_status_commands_total{command=\"update\"}[1m])",
          "legendFormat": "UPDATE",
          "refId": "C"
        },
        {
          "datasource": {
            "type": "prometheus",
            "uid": "prom"
          },
          "expr": "rate(mysql_global_status_commands_total{command=\"delete\"}[1m])",
          "legendFormat": "DELETE",
          "refId": "D"
        }
      ]
    }
  ],
  "schemaVersion": 39,
  "tags": ["mysql", "database", "prometheus"],
  "templating": {
    "list": []
  },
  "time": {
    "from": "now-15m",
    "to": "now"
  },
  "timepicker": {
    "refresh_intervals": [
      "5s",
      "10s",
      "30s",
      "1m",
      "5m",
      "15m"
    ]
  },
  "timezone": "browser",
  "title": "MySQL Overview",
  "uid": "mysql-overview",
  "version": 1,
  "refresh": "10s"
}